{
  "url": "https://jekyllrb.com/",
  "requestedUrl": "https://jekyllrb.com/",
  "timestamp": 1622533686475,
  "ranks": {
    "hundos": 1,
    "performance": 2,
    "accessibility": 2,
    "cumulative": 1
  },
  "lighthouse": {
    "version": "6.5.0",
    "performance": 0.99,
    "accessibility": 1,
    "bestPractices": 1,
    "seo": 1,
    "total": 399
  },
  "firstContentfulPaint": 1053.983,
  "speedIndex": 1053.983,
  "largestContentfulPaint": 2053.947,
  "totalBlockingTime": 139,
  "cumulativeLayoutShift": 0,
  "timeToInteractive": 2278.947,
  "maxPotentialFirstInputDelay": 163,
  "timeToFirstByte": 6.616999999999999,
  "weight": {
    "summary": "10 requests • 196 KiB",
    "total": 201072,
    "image": 72655,
    "imageCount": 3,
    "script": 64333,
    "scriptCount": 2,
    "document": 3623,
    "font": 46357,
    "fontCount": 2,
    "stylesheet": 14040,
    "stylesheetCount": 1,
    "thirdParty": 64397,
    "thirdPartyCount": 3
  },
  "run": {
    "number": 2,
    "total": 3
  },
  "axe": {
    "passes": 242,
    "violations": 6
  }
}